splitscreen_mcp/__init__.py
splitscreen_mcp/__main__.py
splitscreen_mcp/windows_actions.py
computer_split_screen_windows_mcp-0.1.1.dist-info/METADATA
computer_split_screen_windows_mcp-0.1.1.dist-info/WHEEL
computer_split_screen_windows_mcp-0.1.1.dist-info/entry_points.txt
computer_split_screen_windows_mcp-0.1.1.dist-info/licenses/LICENSE
computer_split_screen_windows_mcp-0.1.1.dist-info/RECORD
