Metadata-Version: 2.4
Name: computer-split-screen-windows-mcp
Version: 0.1.1
Summary: MCP server exposing Windows split-screen tools
Author: Computer Split Screen MCP Team
License: MIT License
License-File: LICENSE
Keywords: mcp,pywin32,tiling,windows
Requires-Python: >=3.9
Requires-Dist: mcp>=0.1.0
Provides-Extra: windows
Requires-Dist: pywin32>=306; extra == 'windows'
